qaniujaaqpait/__init__.py
qaniujaaqpait/converter.py
qaniujaaqpait-0.1.1.dist-info/METADATA
qaniujaaqpait-0.1.1.dist-info/WHEEL
qaniujaaqpait-0.1.1.dist-info/top_level.txt
qaniujaaqpait-0.1.1.dist-info/RECORD
