Metadata-Version: 2.4
Name: qaniujaaqpait
Version: 0.1.1
Summary: Fast converter between Inuktitut Unicode syllabics and Latin script
Author: Coleman Haley
License: MIT
Project-URL: Homepage, https://github.com/ColemanHaley/qaniujaaqpait
Keywords: inuktitut,syllabics,converter
Requires-Python: >=3.6
